vrt_lss_routing/__init__.py
vrt_lss_routing/api_client.py
vrt_lss_routing/api_response.py
vrt_lss_routing/configuration.py
vrt_lss_routing/exceptions.py
vrt_lss_routing/py.typed
vrt_lss_routing/rest.py
vrt_lss_routing/api/__init__.py
vrt_lss_routing/api/matrix_api.py
vrt_lss_routing/api/route_api.py
vrt_lss_routing/api/system_api.py
vrt_lss_routing/models/__init__.py
vrt_lss_routing/models/attribute.py
vrt_lss_routing/models/check_result.py
vrt_lss_routing/models/general400.py
vrt_lss_routing/models/general402.py
vrt_lss_routing/models/general404.py
vrt_lss_routing/models/general404_detail.py
vrt_lss_routing/models/general429.py
vrt_lss_routing/models/general500.py
vrt_lss_routing/models/geo_settings.py
vrt_lss_routing/models/geopoint.py
vrt_lss_routing/models/matrix_result.py
vrt_lss_routing/models/matrix_task.py
vrt_lss_routing/models/route.py
vrt_lss_routing/models/route_leg.py
vrt_lss_routing/models/route_result.py
vrt_lss_routing/models/route_statistics.py
vrt_lss_routing/models/route_step.py
vrt_lss_routing/models/route_task.py
vrt_lss_routing/models/route_waypoint.py
vrt_lss_routing/models/routing_matrix.py
vrt_lss_routing/models/routing_matrix_waypoint.py
vrt_lss_routing/models/schema_error.py
vrt_lss_routing/models/service.py
vrt_lss_routing/models/time_window.py
vrt_lss_routing/models/tracedata.py
vrt_lss_routing/models/trackpoint.py
vrt_lss_routing/models/transport_type.py
vrt_lss_routing/models/version_result.py
vrt_lss_routing-7.29.3120.dist-info/METADATA
vrt_lss_routing-7.29.3120.dist-info/WHEEL
vrt_lss_routing-7.29.3120.dist-info/top_level.txt
vrt_lss_routing-7.29.3120.dist-info/RECORD
